yfrake/__init__.py
yfrake/__main__.py
yfrake/cache/__init__.py
yfrake/cache/cache.py
yfrake/cache/const.py
yfrake/cache/utils.py
yfrake/client/__init__.py
yfrake/client/client.py
yfrake/client/decorator.py
yfrake/client/endpoints.py
yfrake/client/exceptions.py
yfrake/client/return_types/__init__.py
yfrake/client/return_types/async_results.py
yfrake/client/return_types/base_response.py
yfrake/client/return_types/base_results.py
yfrake/client/return_types/client_response.py
yfrake/client/return_types/thread_results.py
yfrake/client/session.py
yfrake/client/validators.py
yfrake/client/worker.py
yfrake/config/__init__.py
yfrake/config/config.py
yfrake/config/helpers.py
yfrake/config/utils.py
yfrake/config/validator.py
yfrake/config/yfrake_settings.ini
yfrake/openapi/__init__.py
yfrake/openapi/components.py
yfrake/openapi/generator.py
yfrake/openapi/modules/__init__.py
yfrake/openapi/modules/balance_statements.py
yfrake/openapi/modules/calendar_events.py
yfrake/openapi/modules/cashflow_statements.py
yfrake/openapi/modules/company_overview.py
yfrake/openapi/modules/currencies.py
yfrake/openapi/modules/detailed_summary.py
yfrake/openapi/modules/earnings.py
yfrake/openapi/modules/earnings_history.py
yfrake/openapi/modules/earnings_trend.py
yfrake/openapi/modules/esg_chart.py
yfrake/openapi/modules/esg_scores.py
yfrake/openapi/modules/financials.py
yfrake/openapi/modules/fund_ownership.py
yfrake/openapi/modules/historical_prices.py
yfrake/openapi/modules/income_statements.py
yfrake/openapi/modules/insider_holders.py
yfrake/openapi/modules/insider_transactions.py
yfrake/openapi/modules/insights.py
yfrake/openapi/modules/institution_ownership.py
yfrake/openapi/modules/key_statistics.py
yfrake/openapi/modules/major_holders.py
yfrake/openapi/modules/market_summary.py
yfrake/openapi/modules/news.py
yfrake/openapi/modules/options.py
yfrake/openapi/modules/price_overview.py
yfrake/openapi/modules/purchase_activity.py
yfrake/openapi/modules/quote_type.py
yfrake-2.1.2.dist-info/entry_points.txt
yfrake-2.1.2.dist-info/LICENSE
yfrake-2.1.2.dist-info/WHEEL
yfrake-2.1.2.dist-info/METADATA
yfrake-2.1.2.dist-info/RECORD
