Metadata-Version: 2.1
Name: yfrake
Version: 2.1.2
Summary: A fast and flexible stock market, forex and cryptocurrencies data provider.
License: MIT
Keywords: yahoo,finance,api,server,scraper
Author: Mattias Aabmets
Author-email: mattias.aabmets@gmail.com
Requires-Python: >=3.10,<4.0
Classifier: Development Status :: 5 - Production/Stable
Classifier: Intended Audience :: Developers
Classifier: License :: OSI Approved :: MIT License
Classifier: Operating System :: OS Independent
Classifier: Programming Language :: Python :: 3
Classifier: Programming Language :: Python :: 3.10
Classifier: Topic :: Internet :: WWW/HTTP :: HTTP Servers
Requires-Dist: aiohttp (>=3.8,<3.9)
Requires-Dist: aiohttp-cors (>=0.7,<0.8)
Requires-Dist: aiohttp-swagger3 (>=0.7,<0.8)
Requires-Dist: psutil (>=5.9,<5.10)
Requires-Dist: pyyaml (>=6.0,<6.1)
Requires-Dist: tomli (>=2.0,<2.1)
Project-URL: Documentation, https://yfrake.readthedocs.io
Project-URL: Repository, https://github.com/aspenforest/yfrake
